[{"nome":"Machado de Assis","dataNascimento":"Jul 21, 1839, 12:00:00 AM","nacionalidade":"Brasileiro"},{"nome":"Jorge Amado","dataNascimento":"Sep 10, 1912, 12:00:00 AM","nacionalidade":"Brasileiro"},{"nome":"Clarice Lispector","dataNascimento":"Jan 10, 1921, 12:00:00 AM","nacionalidade":"Brasileira"},{"nome":"José Saramago","dataNascimento":"Dec 16, 1922, 12:00:00 AM","nacionalidade":"Português"},{"nome":"Fernando Pessoa","dataNascimento":"Jul 13, 1888, 12:00:00 AM","nacionalidade":"Português"}]